tronpy_faris/__init__.py
tronpy_faris/abi.py
tronpy_faris/async_contract.py
tronpy_faris/async_tron.py
tronpy_faris/contract.py
tronpy_faris/defaults.py
tronpy_faris/exceptions.py
tronpy_faris/keys/__init__.py
tronpy_faris/providers/__init__.py
tronpy_faris/providers/async_http.py
tronpy_faris/providers/http.py
tronpy_faris/tron.py
tronpy_faris-0.2.6.dist-info/LICENSE
tronpy_faris-0.2.6.dist-info/WHEEL
tronpy_faris-0.2.6.dist-info/METADATA
tronpy_faris-0.2.6.dist-info/RECORD
