Metadata-Version: 2.1
Name: tronpy-faris
Version: 0.2.6
Summary: TRON Python client library
Home-page: https://github.com/andelf/tronpy_faris
License: MIT
Keywords: tron,api,blockchain
Author: andelf
Author-email: andelf@gmail.com
Requires-Python: >=3.6.2,<4.0
Classifier: Development Status :: 2 - Pre-Alpha
Classifier: Intended Audience :: Developers
Classifier: Intended Audience :: System Administrators
Classifier: License :: OSI Approved :: MIT License
Classifier: Natural Language :: English
Classifier: Programming Language :: Python :: 3
Classifier: Programming Language :: Python :: 3.7
Classifier: Topic :: Software Development :: Libraries :: Python Modules
Requires-Dist: base58 (>=2.0.0,<3.0.0)
Requires-Dist: ecdsa (>=0.17,<0.18)
Requires-Dist: eth_abi (>=2.1.1,<3.0.0)
Requires-Dist: httpx (>=0.22,<0.23)
Requires-Dist: pycryptodome (>=3.9.7,<4.0.0)
Requires-Dist: requests (>=2.23.0,<3.0.0)
Project-URL: Repository, https://github.com/andelf/tronpy_faris
